CHANGELOG.md
README.md
mitol/__init__.py
mitol/scim/README.md
mitol/scim/__init__.py
mitol/scim/adapters.py
mitol/scim/api.py
mitol/scim/apps.py
mitol/scim/config.py
mitol/scim/constants.py
mitol/scim/filters.py
mitol/scim/forms.py
mitol/scim/parser.py
mitol/scim/requests.py
mitol/scim/tasks.py
mitol/scim/urls.py
mitol/scim/utils.py
mitol/scim/views.py
mitol/scim/management/__init__.py
mitol/scim/management/commands/__init__.py
mitol/scim/management/commands/scim_sync.py
mitol/scim/settings/__init__.py
mitol/scim/settings/scim.py
mitol_django_scim-2025.7.29.dist-info/METADATA
mitol_django_scim-2025.7.29.dist-info/WHEEL
mitol_django_scim-2025.7.29.dist-info/RECORD
