Metadata-Version: 2.4
Name: mitol-django-scim
Version: 2025.7.29
Summary: Django application for SCIM integrations
License-Expression: BSD-3-Clause
Requires-Python: >=3.10
Requires-Dist: django-scim2>=0.19.1
Requires-Dist: django-stubs>=1.13.1
Requires-Dist: django>=3.0
Requires-Dist: mitol-django-common
Requires-Dist: pyparsing>=3.2
Requires-Dist: requests>=2.32.0
Requires-Dist: strenum>=0.4.15
Requires-Dist: strenum>=0.4.15; python_version < '3.11'
Provides-Extra: celery
Requires-Dist: mitol-django-common[celery]; extra == 'celery'
